src/datasources/__about__.py
src/datasources/__init__.py
timeseriesdatasources-0.0.2.dist-info/METADATA
timeseriesdatasources-0.0.2.dist-info/WHEEL
timeseriesdatasources-0.0.2.dist-info/licenses/LICENSE.txt
timeseriesdatasources-0.0.2.dist-info/RECORD
