Metadata-Version: 2.1
Name: timeseriesdatasources
Version: 0.0.2
Project-URL: Documentation, https://github.com/fenke/datasources#readme
Project-URL: Issues, https://github.com/fenke/datasources/issues
Project-URL: Source, https://github.com/fenke/datasources
Author-email: fenke <fenkemeijer@gmail.com>
License-Expression: MIT
License-File: LICENSE.txt
Classifier: Development Status :: 4 - Beta
Classifier: Programming Language :: Python
Classifier: Programming Language :: Python :: 3.7
Classifier: Programming Language :: Python :: 3.8
Classifier: Programming Language :: Python :: 3.9
Classifier: Programming Language :: Python :: 3.10
Classifier: Programming Language :: Python :: 3.11
Classifier: Programming Language :: Python :: Implementation :: CPython
Classifier: Programming Language :: Python :: Implementation :: PyPy
Requires-Python: >=3.7
